astToolkit/__init__.py
astToolkit/_astTypes.py
astToolkit/_dumpHandmade.py
astToolkit/_theSSOT.py
astToolkit/_toolBe.py
astToolkit/_toolDOT.py
astToolkit/_toolGrab.py
astToolkit/_toolIfThis.py
astToolkit/_toolMake.py
astToolkit/_toolThen.py
astToolkit/_toolkitAST.py
astToolkit/_toolkitNodeVisitor.py
astToolkit/containers.py
astToolkit/py.typed
astToolkit/transformationTools.py
asttoolkit-0.11.0.dist-info/licenses/LICENSE
notesClassFind/_generateStubFind.py
notesClassFind/_prototypeFind.py
notesClassFind/_prototypeFind.pyi
notesClassFind/_toolBeMetaclasses.py
notesClassFind/idea_compare traversals.py
notesClassFind/pseudocode.py
notesClassFind/zz.py
tests/__init__.py
tests/conftest.py
tests/test_Be.py
tests/test_Containers.py
tests/test_Grab.py
tests/test_IfThis.py
tests/test_Then.py
tests/test_toolkitAST.py
tests/test_transformationTools.py
tests/dataSamples/Make.py
tests/dataSamples/__init__.py
tests/dataSamples/createTestData.py
tests/dataSamples/sampleModuleForParsing.py
asttoolkit-0.11.0.dist-info/METADATA
asttoolkit-0.11.0.dist-info/WHEEL
asttoolkit-0.11.0.dist-info/top_level.txt
asttoolkit-0.11.0.dist-info/RECORD
