Metadata-Version: 2.4
Name: astToolkit
Version: 0.11.0
Summary: A powerfully composable, type-safe toolkit for Python abstract syntax tree (AST) manipulation, analysis, transformation, and code generation with a layered architecture designed for building sophisticated code processing assembly-lines.
Author-email: Hunter Hogan <HunterHogan@pm.me>
License: CC-BY-NC-4.0
Project-URL: Donate, https://www.patreon.com/integrated
Project-URL: Homepage, https://github.com/hunterhogan/astToolkit
Project-URL: Issues, https://github.com/hunterhogan/astToolkit/issues
Project-URL: Repository, https://github.com/hunterhogan/astToolkit.git
Keywords: abstract syntax tree,ast,ast-analysis,ast-manipulation,ast-predicate,ast-traversal,ast-visitor,code-analysis,code-refactoring,code generation,code transformation,composable-apis,function-inlining,metaprogramming,python-ast,source-code-generation,static-analysis,type-safe,typed-ast,visitor-pattern
Classifier: Development Status :: 4 - Beta
Classifier: Environment :: Console
Classifier: Intended Audience :: Developers
Classifier: Intended Audience :: Science/Research
Classifier: Natural Language :: English
Classifier: Operating System :: OS Independent
Classifier: Programming Language :: Python
Classifier: Programming Language :: Python :: 3
Classifier: Programming Language :: Python :: 3.13
Classifier: Programming Language :: Python :: 3.14
Classifier: Topic :: Scientific/Engineering :: Information Analysis
Classifier: Topic :: Software Development :: Code Generators
Classifier: Topic :: Software Development :: Libraries :: Python Modules
Classifier: Typing :: Typed
Requires-Python: >=3.13
License-File: LICENSE
Requires-Dist: hunterMakesPy>=0.3.0
Provides-Extra: development
Requires-Dist: setuptools-scm; extra == "development"
Provides-Extra: testing
Requires-Dist: pytest-cov; extra == "testing"
Requires-Dist: pytest-xdist; extra == "testing"
Requires-Dist: pytest; extra == "testing"
Dynamic: license-file
